genall/__init__.py
genall/__main__.py
genall/codegen.py
genall/genall.py
genall/main.py
genall/parsing.py
genall/py.typed
genall/filters/__init__.py
genall/filters/file_filter.py
genall-0.0.5.dist-info/licenses/LICENSE
genall-0.0.5.dist-info/METADATA
genall-0.0.5.dist-info/WHEEL
genall-0.0.5.dist-info/entry_points.txt
genall-0.0.5.dist-info/top_level.txt
genall-0.0.5.dist-info/RECORD
