Metadata-Version: 2.4
Name: genall
Version: 0.0.5
Summary: Add your description here
Author-email: Alex Rudolph <alex@voker.ai>
License: Copyright 2025-current Alex Rudolph
Requires-Python: >=3.13
License-File: LICENSE
Requires-Dist: click>=8.3.1
Requires-Dist: libcst>=1.8.6
Requires-Dist: pathspec>=0.12.1
Requires-Dist: pyyaml>=6.0.3
Requires-Dist: rich>=14.2.0
Dynamic: license-file
